BUAACrypto2024/Basic_Code.py
BUAACrypto2024/__init__.py
BUAACrypto2024/cal.py
BUAACrypto2024-0.0.8.data/data/requirements.txt
BUAACrypto2024-0.0.8.dist-info/METADATA
BUAACrypto2024-0.0.8.dist-info/WHEEL
BUAACrypto2024-0.0.8.dist-info/top_level.txt
BUAACrypto2024-0.0.8.dist-info/RECORD
