Metadata-Version: 2.1
Name: BUAACrypto2024
Version: 0.0.8
Summary: this is a simple crypto packet for some cryptomatic algorithm
Author: pyrjx
Author-email: 3441252502@qq.com
Classifier: Programming Language :: Python :: 3
Classifier: License :: OSI Approved :: MIT License
Classifier: Operating System :: OS Independent
Requires-Python: >=3.6
